cloe_logging/__init__.py
cloe_logging/logger_factory.py
cloe_logging/py.typed
cloe_logging/decorators/__init__.py
cloe_logging/decorators/devops_decorator.py
cloe_logging/formatters/__init__.py
cloe_logging/formatters/devops_formatter.py
cloe_logging/formatters/dict_formatter.py
cloe_logging/handlers/__init__.py
cloe_logging/handlers/log_analytics_handler.py
cloe_logging/handlers/snowflake_handler.py
cloe_logging/handlers/unity_catalog_handler.py
cloe_logging/utility/__init__.py
cloe_logging/utility/serializer.py
cloe_logging-0.3.10.dist-info/METADATA
cloe_logging-0.3.10.dist-info/WHEEL
cloe_logging-0.3.10.dist-info/RECORD
