Metadata-Version: 2.4
Name: cloe-logging
Version: 0.3.10
Summary: A Standardized Solution for logging to various targets.
Author-email: David Achilles <david.achilles@accenture.com>, Ole Steinbrueck <ole.steinbrueck@accenture.com>
License: Proprietary
Classifier: Development Status :: 5 - Production/Stable
Classifier: Environment :: Console
Classifier: Intended Audience :: Developers
Classifier: License :: Other/Proprietary License
Classifier: Operating System :: OS Independent
Classifier: Programming Language :: Python :: 3.11
Classifier: Programming Language :: Python :: 3.12
Classifier: Topic :: Database
Requires-Python: <3.14,>=3.11
Requires-Dist: pydantic<3.0.0,>=2.7.0
Requires-Dist: typing-extensions<5.0.0,>=4.12.2
Provides-Extra: databricks
Requires-Dist: databricks-sdk>=0.39.0; extra == 'databricks'
Provides-Extra: log-analytics
Requires-Dist: requests<3.0.0,>=2.31.0; extra == 'log-analytics'
Provides-Extra: snowflake
Requires-Dist: cloe-util-snowflake-connector<2.0.0,>=1.0.2; extra == 'snowflake'
